balanced/__init__.py
balanced/config.py
balanced/exc.py
balanced/resources.py
balanced/utils.py
balanced-1.2.dist-info/DESCRIPTION.rst
balanced-1.2.dist-info/METADATA
balanced-1.2.dist-info/metadata.json
balanced-1.2.dist-info/RECORD
balanced-1.2.dist-info/top_level.txt
balanced-1.2.dist-info/WHEEL
