Metadata-Version: 2.0
Name: balanced
Version: 1.2
Summary: Payments platform for marketplaces
Home-page: https://balancedpayments.com/
Author: Balanced
Author-email: dev@balancedpayments.com
License: MIT License
Platform: UNKNOWN
Classifier: Intended Audience :: Developers
Classifier: License :: OSI Approved :: MIT License
Classifier: Programming Language :: Python
Classifier: Topic :: Software Development :: Libraries :: Python Modules
Requires-Dist: wac (==0.23)
Requires-Dist: iso8601 (==0.1.4)
Requires-Dist: uritemplate (==0.6)
